tfrecord/TFRecordClass.py
tfrecord/__init__.py
easy_tfrecord-0.3.dist-info/METADATA
easy_tfrecord-0.3.dist-info/WHEEL
easy_tfrecord-0.3.dist-info/top_level.txt
easy_tfrecord-0.3.dist-info/RECORD
