Metadata-Version: 2.1
Name: easy-tfrecord
Version: 0.3
Summary: TF Records for image classification.
Home-page: https://github.com/Wangsherpa/easy_tfrecord
Author: Wang Sherpa
Author-email: wangdoje@gmail.com
License: UNKNOWN
Platform: UNKNOWN
Classifier: Programming Language :: Python :: 3
Classifier: License :: OSI Approved :: MIT License
Classifier: Operating System :: OS Independent
Requires-Python: >=3.6
